amazonreviewscrap/__init__.py
amazonreviewscrap/scrap_data.py
amazonreviewscrap/selenium_data_download.py
amazonreviewscrap-0.1.dist-info/METADATA
amazonreviewscrap-0.1.dist-info/WHEEL
amazonreviewscrap-0.1.dist-info/top_level.txt
amazonreviewscrap-0.1.dist-info/RECORD
